{
  "kind": "collectionType",
  "collectionName": "socials",
  "info": {
    "singularName": "social",
    "pluralName": "socials",
    "displayName": "Social",
    "description": ""
  },
  "options": {
    "draftAndPublish": true
  },
  "pluginOptions": {},
  "attributes": {
    "name": {
      "type": "string"
    },
    "url": {
      "type": "string"
    },
    "image": {
      "allowedTypes": [
        "images",
        "files",
        "videos",
        "audios"
      ],
      "type": "media",
      "multiple": false
    }
  }
}
